expliot/__init__.py
expliot/constants.py
expliot/core/__init__.py
expliot/core/bom/__init__.py
expliot/core/bom/cdx/__init__.py
expliot/core/bom/cdx/json14schema.py
expliot/core/common/__init__.py
expliot/core/common/disclosure.py
expliot/core/common/exceptions.py
expliot/core/common/fileutils.py
expliot/core/common/pcapdlt.py
expliot/core/common/pcaphelper.py
expliot/core/common/timer.py
expliot/core/discovery/__init__.py
expliot/core/interfaces/__init__.py
expliot/core/interfaces/busauditor/__init__.py
expliot/core/interfaces/busauditor/stm32f411.py
expliot/core/interfaces/common_services.py
expliot/core/interfaces/ftdi/__init__.py
expliot/core/interfaces/zbauditor/__init__.py
expliot/core/interfaces/zbauditor/nrf52840.py
expliot/core/protocols/__init__.py
expliot/core/protocols/hardware/__init__.py
expliot/core/protocols/hardware/can/__init__.py
expliot/core/protocols/hardware/i2c/__init__.py
expliot/core/protocols/hardware/serial/__init__.py
expliot/core/protocols/hardware/spi/__init__.py
expliot/core/protocols/internet/__init__.py
expliot/core/protocols/internet/coap/__init__.py
expliot/core/protocols/internet/dicom/__init__.py
expliot/core/protocols/internet/mdns/__init__.py
expliot/core/protocols/internet/mdns/constants.py
expliot/core/protocols/internet/modbus/__init__.py
expliot/core/protocols/internet/mqtt/__init__.py
expliot/core/protocols/internet/mqtt/aws.py
expliot/core/protocols/internet/tls/__init__.py
expliot/core/protocols/internet/upnp/__init__.py
expliot/core/protocols/radio/__init__.py
expliot/core/protocols/radio/ble/__init__.py
expliot/core/protocols/radio/dot154/__init__.py
expliot/core/protocols/radio/dot154/dot154_utils.py
expliot/core/protocols/radio/zigbee/__init__.py
expliot/core/protocols/radio/zigbee/zigbee_utils.py
expliot/core/tests/__init__.py
expliot/core/tests/test.py
expliot/core/tests/testsuite.py
expliot/core/ui/__init__.py
expliot/core/ui/cli/__init__.py
expliot/core/vendors/__init__.py
expliot/core/vendors/tplink/__init__.py
expliot-0.11.1.dist-info/LICENSE.txt
expliot-0.11.1.dist-info/METADATA
expliot-0.11.1.dist-info/WHEEL
expliot-0.11.1.dist-info/entry_points.txt
expliot-0.11.1.dist-info/RECORD
